UndetectedChrome/__init__.py
UndetectedChrome/cli.py
UndetectedChrome/undetected_chrome.py
UndetectedChrome/undetected_chrome_old.py
undetectedchrome-0.3.0.dist-info/licenses/LICENSE
undetectedchrome-0.3.0.dist-info/METADATA
undetectedchrome-0.3.0.dist-info/WHEEL
undetectedchrome-0.3.0.dist-info/entry_points.txt
undetectedchrome-0.3.0.dist-info/top_level.txt
undetectedchrome-0.3.0.dist-info/RECORD
