Metadata-Version: 2.4
Name: UndetectedChrome
Version: 0.3.0
Summary: A comprehensive browser automation class using nodriver.
Home-page: https://github.com/guocity/UndetectedChrome
Author: guocity
Author-email: your.email@example.com
Classifier: Programming Language :: Python :: 3
Classifier: License :: OSI Approved :: MIT License
Classifier: Operating System :: OS Independent
Requires-Python: >=3.7
License-File: LICENSE
Requires-Dist: nodriver
Requires-Dist: websockets
Dynamic: author
Dynamic: author-email
Dynamic: classifier
Dynamic: home-page
Dynamic: license-file
Dynamic: requires-dist
Dynamic: requires-python
Dynamic: summary
